pynando/__init__.py
pynando/data.py
pynando/downloader.py
pynando/nando.py
pynando-0.0.11.dist-info/LICENSE
pynando-0.0.11.dist-info/METADATA
pynando-0.0.11.dist-info/WHEEL
pynando-0.0.11.dist-info/top_level.txt
pynando-0.0.11.dist-info/RECORD
