Metadata-Version: 2.1
Name: pynando
Version: 0.0.11
Summary: wrapper for Nando (Nanbyo data ontology)
Home-page: https://github.com/roy29fuku/pynando
Author: Ryota Yamada
Author-email: roy29fuku@gmail.com
License: UNKNOWN
Platform: UNKNOWN
Classifier: Programming Language :: Python :: 3
Classifier: Programming Language :: Python :: 3.8
Classifier: License :: OSI Approved :: MIT License
Classifier: Operating System :: MacOS
Requires-Python: >=3.8
Requires-Dist: gitdb2 (==3.0.2)
Requires-Dist: GitPython (==3.0.8)
Requires-Dist: smmap2 (==2.0.5)
